.travis.yml
CHANGES.rst
MANIFEST.in
README.rst
setup.py
tox.ini
/home/blackwithwhite/Work/ged-soa/stats/src/pyhashring/src/hash_ring.c
/home/blackwithwhite/Work/ged-soa/stats/src/pyhashring/src/md5.c
/home/blackwithwhite/Work/ged-soa/stats/src/pyhashring/src/sha1.c
/home/blackwithwhite/Work/ged-soa/stats/src/pyhashring/src/sort.c
pyhashring/__init__.py
pyhashring/ring.c
pyhashring/ring.pyx
pyhashring.egg-info/PKG-INFO
pyhashring.egg-info/SOURCES.txt
pyhashring.egg-info/dependency_links.txt
pyhashring.egg-info/not-zip-safe
pyhashring.egg-info/top_level.txt
pyhashring/tests/__init__.py
pyhashring/tests/base.py
pyhashring/tests/test_ring.py
src/hash_ring.c
src/hash_ring.h
src/md5.c
src/md5.h
src/sha1.c
src/sha1.h
src/sort.c
src/sort.h